setup.py
distributions_mahesh_test/Binomialdistribution.py
distributions_mahesh_test/Gaussiandistribution.py
distributions_mahesh_test/Generaldistribution.py
distributions_mahesh_test/__init__.py
distributions_mahesh_test.egg-info/PKG-INFO
distributions_mahesh_test.egg-info/SOURCES.txt
distributions_mahesh_test.egg-info/dependency_links.txt
distributions_mahesh_test.egg-info/not-zip-safe
distributions_mahesh_test.egg-info/top_level.txt