Metadata-Version: 1.0
Name: distributions-mahesh-test
Version: 0.1
Summary: Gaussian distributions
Home-page: UNKNOWN
Author: Mahesh Sonavane
Author-email: mahesh.sonavane14@hotmail.com
License: UNKNOWN
Platform: UNKNOWN
